{
  "collectionName": "components_form_textfields",
  "info": {
    "displayName": "TextField",
    "description": "",
    "icon": "layer"
  },
  "options": {},
  "attributes": {
    "type": {
      "type": "enumeration",
      "enum": [
        "email",
        "text",
        "password",
        "number"
      ],
      "required": true
    },
    "placeholder": {
      "type": "string",
      "maxLength": 15
    },
    "multiline": {
      "type": "boolean",
      "default": false
    },
    "required": {
      "type": "boolean",
      "default": false
    },
    "name": {
      "type": "string",
      "required": true,
      "unique": false,
      "minLength": 2,
      "regex": "^[a-zA-Z]+$"
    },
    "label": {
      "type": "string",
      "required": true,
      "unique": false,
      "minLength": 2
    }
  }
}
